unaiverse/__init__.py
unaiverse/agent.py
unaiverse/agent_basics.py
unaiverse/clock.py
unaiverse/dataprops.py
unaiverse/hsm.py
unaiverse/stats.py
unaiverse/streams.py
unaiverse/world.py
unaiverse/modules/__init__.py
unaiverse/modules/networks.py
unaiverse/modules/utils.py
unaiverse/modules/cnu/__init__.py
unaiverse/modules/cnu/cnus.py
unaiverse/modules/cnu/layers.py
unaiverse/modules/cnu/psi.py
unaiverse/modules/hl/__init__.py
unaiverse/modules/hl/hl_utils.py
unaiverse/networking/__init__.py
unaiverse/networking/node/__init__.py
unaiverse/networking/node/connpool.py
unaiverse/networking/node/node.py
unaiverse/networking/node/profile.py
unaiverse/networking/node/tokens.py
unaiverse/networking/p2p/__init__.py
unaiverse/networking/p2p/go.mod
unaiverse/networking/p2p/go.sum
unaiverse/networking/p2p/golibp2p.py
unaiverse/networking/p2p/golibp2p.pyi
unaiverse/networking/p2p/lib.go
unaiverse/networking/p2p/lib_types.py
unaiverse/networking/p2p/message_pb2.py
unaiverse/networking/p2p/messages.py
unaiverse/networking/p2p/mylogger.py
unaiverse/networking/p2p/p2p.py
unaiverse/networking/p2p/proto-go/message.pb.go
unaiverse/streamlib/__init__.py
unaiverse/streamlib/streamlib.py
unaiverse/utils/__init__.py
unaiverse/utils/lone_wolf.json
unaiverse/utils/misc.py
unaiverse/utils/sandbox.py
unaiverse-0.1.14.dist-info/licenses/LICENSE
unaiverse-0.1.14.dist-info/METADATA
unaiverse-0.1.14.dist-info/WHEEL
unaiverse-0.1.14.dist-info/top_level.txt
unaiverse-0.1.14.dist-info/RECORD
