Metadata-Version: 2.4
Name: unaiverse
Version: 0.1.14
Summary: UNaIVERSE: A Collectionless AI Project. The new web of humans & AI Agents, built on privacy, control, and reduced energy consumption.
Author-email: Stefano Melacci <stefano.melacci@unisi.it>, Christian Di Maio <christian.dimaio@phd.unipi.it>, Tommaso Guidi <tommaso.guidi.1998@gmail.com>
Maintainer-email: Stefano Melacci <stefano.melacci@unisi.it>, Christian Di Maio <christian.dimaio@phd.unipi.it>, Tommaso Guidi <tommaso.guidi.1998@gmail.com>
Project-URL: A-Homepage, https://unaiverse.io
Project-URL: B-CollectionlessAI, https://collectionless.ai
Project-URL: C-Source, https://github.com/collectionlessai/unaiverse-src
Project-URL: D-Starting, https://github.com/collectionlessai/unaiverse-src/blob/main/README.md
Project-URL: E-Examples, https://github.com/collectionlessai/unaiverse-examples
Project-URL: F-Documentation, https://github.com/collectionlessai/unaiverse-src/blob/main/README.md
Keywords: UNaIVERSE,Collectionless AI,AI,Agentic AI,Agents,Machine Learning,Learning Over Time
Classifier: Development Status :: 4 - Beta
Classifier: Intended Audience :: Developers
Classifier: Intended Audience :: End Users/Desktop
Classifier: Intended Audience :: Science/Research
Classifier: Programming Language :: Python :: 3.11
Classifier: Programming Language :: Python :: 3.12
Classifier: Topic :: Scientific/Engineering :: Artificial Intelligence
Requires-Python: >3.10
License-File: LICENSE
Requires-Dist: opencv-python
Requires-Dist: Flask
Requires-Dist: flask_cors
Requires-Dist: graphviz
Requires-Dist: ntplib
Requires-Dist: numpy
Requires-Dist: Pillow
Requires-Dist: protobuf
Requires-Dist: psutil
Requires-Dist: PyJWT
Requires-Dist: cryptography
Requires-Dist: Requests
Requires-Dist: torch
Requires-Dist: torchvision
Requires-Dist: transformers
Requires-Dist: sortedcontainers
Requires-Dist: plotly
Dynamic: license-file
